laive/__init__.py
laive/sdk.py
laive_sdk-0.1.0.dist-info/licenses/LICENSE
laive_sdk-0.1.0.dist-info/METADATA
laive_sdk-0.1.0.dist-info/WHEEL
laive_sdk-0.1.0.dist-info/top_level.txt
laive_sdk-0.1.0.dist-info/RECORD
