Metadata-Version: 2.4
Name: laive-sdk
Version: 0.1.0
Summary: Python SDK for the Laive RAG API
Home-page: https://github.com/laiveai/Python-SDK
Author: Laive
Author-email: Laive <contact@laive.ai>
License: MIT
Project-URL: Homepage, https://github.com/laive/Python-SDK
Project-URL: Documentation, https://github.com/laive/Python-SDK#readme
Project-URL: Repository, https://github.com/laive/Python-SDK.git
Project-URL: Bug Reports, https://github.com/laive/Python-SDK/issues
Keywords: laive,rag,retrieval,augmented,generation,ai,nlp,sdk
Classifier: Development Status :: 4 - Beta
Classifier: Intended Audience :: Developers
Classifier: License :: OSI Approved :: MIT License
Classifier: Operating System :: OS Independent
Classifier: Programming Language :: Python :: 3
Classifier: Programming Language :: Python :: 3.7
Classifier: Programming Language :: Python :: 3.8
Classifier: Programming Language :: Python :: 3.9
Classifier: Programming Language :: Python :: 3.10
Classifier: Programming Language :: Python :: 3.11
Classifier: Programming Language :: Python :: 3.12
Classifier: Topic :: Software Development :: Libraries :: Python Modules
Classifier: Topic :: Scientific/Engineering :: Artificial Intelligence
Classifier: Topic :: Text Processing :: Linguistic
Requires-Python: >=3.7
License-File: LICENSE
Requires-Dist: requests>=2.25.0
Requires-Dist: rich>=10.0.0
Provides-Extra: dev
Requires-Dist: pytest>=6.0; extra == "dev"
Requires-Dist: black>=21.0; extra == "dev"
Requires-Dist: flake8>=3.8; extra == "dev"
Requires-Dist: mypy>=0.900; extra == "dev"
Provides-Extra: notebooks
Requires-Dist: jupyter>=1.0.0; extra == "notebooks"
Requires-Dist: ipykernel>=6.0.0; extra == "notebooks"
Dynamic: author
Dynamic: home-page
Dynamic: license-file
Dynamic: requires-python
